Metadata-Version: 1.0
Name: simpledsapp-moc
Version: 1.0.0
Summary: A simple DS type ChRIS application specifically created for the Massachusetts Open Cloud remote computing environment.
Home-page: http://wiki
Author: FNNDSC
Author-email: dev@babyMRI.org
License: MIT
Platform: UNKNOWN
